LICENSE
MANIFEST.in
README.md
pyproject.toml
setup.py
pynq_dpu/__init__.py
pynq_dpu/dpu.bit.link
pynq_dpu/dpu.hwh.link
pynq_dpu/dpu.py
pynq_dpu/dpu.xclbin.link
pynq_dpu.egg-info/PKG-INFO
pynq_dpu.egg-info/SOURCES.txt
pynq_dpu.egg-info/dependency_links.txt
pynq_dpu.egg-info/entry_points.txt
pynq_dpu.egg-info/requires.txt
pynq_dpu.egg-info/top_level.txt
pynq_dpu/notebooks/dpu_mnist_classifier.ipynb
pynq_dpu/notebooks/dpu_mnist_classifier.xmodel.link
pynq_dpu/notebooks/dpu_resnet50.ipynb
pynq_dpu/notebooks/dpu_resnet50.xmodel.link
pynq_dpu/notebooks/dpu_resnet50_pybind11.ipynb
pynq_dpu/notebooks/dpu_tf_inceptionv1.ipynb
pynq_dpu/notebooks/dpu_tf_inceptionv1.xmodel.link
pynq_dpu/notebooks/dpu_yolov3.ipynb
pynq_dpu/notebooks/tf_yolov3_voc.xmodel.link
pynq_dpu/notebooks/img/bellpeppe-994958.JPEG
pynq_dpu/notebooks/img/greyfox-672194.JPEG
pynq_dpu/notebooks/img/irishterrier-696543.JPEG
pynq_dpu/notebooks/img/jinrikisha-911722.JPEG
pynq_dpu/notebooks/img/voc_classes.txt
pynq_dpu/notebooks/img/words.txt
pynq_dpu/tests/__init__.py
pynq_dpu/tests/test_vart.py
pynq_dpu/tests/test_xrt.py
pynq_dpu/tests/models/dpu_resnet50.xmodel.link