Metadata-Version: 2.1
Name: pynq-dpu
Version: 2.5.1
Summary: PYNQ DPU Overlay using Vitis AI
Home-page: https://github.com/Xilinx/DPU-PYNQ.git
Author: Xilinx PYNQ Development Team
License: Apache License 2.0
Platform: UNKNOWN
Requires-Python: >=3.10.0
License-File: LICENSE
